README.rst
setup.py
sbt_python_client.egg-info/PKG-INFO
sbt_python_client.egg-info/SOURCES.txt
sbt_python_client.egg-info/dependency_links.txt
sbt_python_client.egg-info/requires.txt
sbt_python_client.egg-info/top_level.txt
solutions_by_text/__init__.py
solutions_by_text/base.py
solutions_by_text/carrier.py
solutions_by_text/handle_exceptions.py
solutions_by_text/message.py
solutions_by_text/sbt_token_generator.py
solutions_by_text/subscriber.py
solutions_by_text/utils.py
tests/__init__.py
tests/conftest.py
tests/test_api.py