Metadata-Version: 1.0
Name: sbt-python-client
Version: 1.0.5
Summary: A python implementation of solutionsbytext REST API
Home-page: https://github.com/sijanonly/sbt-python-client
Author: Sijan Bhandari
Author-email: sijanonly@gmail.com
License: MIT
Platform: UNKNOWN
